{"trial_id": "d0c2774607dfeeb156be35e7823ea010", "hyperparameters": {"space": [{"class_name": "Int", "config": {"name": "units_1", "default": null, "conditions": [], "min_value": 4, "max_value": 32, "step": 2, "sampling": null}}, {"class_name": "Choice", "config": {"name": "dense_activation_1", "default": "relu", "conditions": [], "values": ["relu", "tanh", "sigmoid"], "ordered": false}}, {"class_name": "Int", "config": {"name": "units_2", "default": null, "conditions": [], "min_value": 4, "max_value": 32, "step": 2, "sampling": null}}, {"class_name": "Choice", "config": {"name": "dense_activation_2", "default": "relu", "conditions": [], "values": ["relu", "tanh", "sigmoid"], "ordered": false}}], "values": {"units_1": 28, "dense_activation_1": "relu", "units_2": 14, "dense_activation_2": "tanh", "tuner/epochs": 3, "tuner/initial_epoch": 0, "tuner/bracket": 4, "tuner/round": 0}}, "metrics": {"metrics": {"loss": {"direction": "min", "observations": [{"value": [1.2209115028381348], "step": 0}]}, "auc": {"direction": "max", "observations": [{"value": [0.5597363710403442], "step": 0}]}, "val_loss": {"direction": "min", "observations": [{"value": [1.5759141445159912], "step": 0}]}, "val_auc": {"direction": "min", "observations": [{"value": [0.46707454323768616], "step": 0}]}}}, "score": 0.5597363710403442, "best_step": 0, "status": "COMPLETED"}