{"trial_id": "de035daa52a4c9cec0bc06e1c005b96b", "hyperparameters": {"space": [{"class_name": "Int", "config": {"name": "units_1", "default": null, "conditions": [], "min_value": 4, "max_value": 32, "step": 2, "sampling": null}}, {"class_name": "Int", "config": {"name": "units_2", "default": null, "conditions": [], "min_value": 4, "max_value": 32, "step": 2, "sampling": null}}], "values": {"units_1": 30, "units_2": 20, "tuner/epochs": 3, "tuner/initial_epoch": 0, "tuner/bracket": 4, "tuner/round": 0}}, "metrics": {"metrics": {"loss": {"direction": "min", "observations": [{"value": [192.91159057617188], "step": 0}]}, "auc": {"direction": "max", "observations": [{"value": [0.516258955001831], "step": 0}]}, "val_loss": {"direction": "min", "observations": [{"value": [112.54154968261719], "step": 0}]}, "val_auc": {"direction": "min", "observations": [{"value": [0.5], "step": 0}]}}}, "score": 0.516258955001831, "best_step": 0, "status": "COMPLETED"}