{"trial_id": "af106b81a6f35852b26ec6f0db75f7d4", "hyperparameters": {"space": [{"class_name": "Int", "config": {"name": "units_1", "default": null, "conditions": [], "min_value": 4, "max_value": 32, "step": 2, "sampling": null}}, {"class_name": "Int", "config": {"name": "units_2", "default": null, "conditions": [], "min_value": 4, "max_value": 32, "step": 2, "sampling": null}}, {"class_name": "Int", "config": {"name": "units_3", "default": null, "conditions": [], "min_value": 4, "max_value": 32, "step": 2, "sampling": null}}], "values": {"units_1": 6, "units_2": 22, "units_3": 28, "tuner/epochs": 19, "tuner/initial_epoch": 7, "tuner/bracket": 5, "tuner/round": 2, "tuner/trial_id": "7b29622534d63c04da2da3dd5e389a4c"}}, "metrics": {"metrics": {"loss": {"direction": "min", "observations": [{"value": [416.8750305175781], "step": 0}]}, "auc": {"direction": "max", "observations": [{"value": [0.5187238454818726], "step": 0}]}, "val_loss": {"direction": "min", "observations": [{"value": [79.52661895751953], "step": 0}]}, "val_auc": {"direction": "min", "observations": [{"value": [0.503164529800415], "step": 0}]}}}, "score": 0.5187238454818726, "best_step": 0, "status": "COMPLETED"}