{"trial_id": "4b637c292b0120f2ba859754a6e18c3d", "hyperparameters": {"space": [{"class_name": "Int", "config": {"name": "units_1", "default": null, "conditions": [], "min_value": 8, "max_value": 32, "step": 2, "sampling": null}}, {"class_name": "Choice", "config": {"name": "dense_activation_1", "default": "relu", "conditions": [], "values": ["relu", "tanh", "sigmoid", "elu"], "ordered": false}}, {"class_name": "Int", "config": {"name": "units_2", "default": null, "conditions": [], "min_value": 8, "max_value": 32, "step": 2, "sampling": null}}, {"class_name": "Choice", "config": {"name": "dense_activation_2", "default": "relu", "conditions": [], "values": ["relu", "tanh", "sigmoid", "elu"], "ordered": false}}, {"class_name": "Int", "config": {"name": "units_3", "default": null, "conditions": [], "min_value": 8, "max_value": 32, "step": 2, "sampling": null}}, {"class_name": "Choice", "config": {"name": "dense_activation_3", "default": "relu", "conditions": [], "values": ["relu", "tanh", "sigmoid", "elu"], "ordered": false}}, {"class_name": "Int", "config": {"name": "units_4", "default": null, "conditions": [], "min_value": 8, "max_value": 32, "step": 2, "sampling": null}}, {"class_name": "Choice", "config": {"name": "dense_activation_4", "default": "relu", "conditions": [], "values": ["relu", "tanh", "sigmoid", "elu"], "ordered": false}}], "values": {"units_1": 22, "dense_activation_1": "tanh", "units_2": 12, "dense_activation_2": "sigmoid", "units_3": 8, "dense_activation_3": "relu", "units_4": 30, "dense_activation_4": "elu", "tuner/epochs": 5, "tuner/initial_epoch": 0, "tuner/bracket": 5, "tuner/round": 0}}, "metrics": {"metrics": {"loss": {"direction": "min", "observations": [{"value": [0.7340235114097595], "step": 0}]}, "auc": {"direction": "max", "observations": [{"value": [0.5630701780319214], "step": 0}]}, "val_loss": {"direction": "min", "observations": [{"value": [0.7069747447967529], "step": 0}]}, "val_auc": {"direction": "min", "observations": [{"value": [0.5395857095718384], "step": 0}]}}}, "score": 0.5630701780319214, "best_step": 0, "status": "COMPLETED"}