{"trial_id": "2d4bddb31ed80a455b5ab306c7254f78", "hyperparameters": {"space": [{"class_name": "Int", "config": {"name": "units", "default": null, "conditions": [], "min_value": 4, "max_value": 32, "step": 2, "sampling": null}}], "values": {"units": 14, "tuner/epochs": 3, "tuner/initial_epoch": 0, "tuner/bracket": 4, "tuner/round": 0}}, "metrics": {"metrics": {"loss": {"direction": "min", "observations": [{"value": [261.39013671875], "step": 0}]}, "auc": {"direction": "max", "observations": [{"value": [0.5295683145523071], "step": 0}]}, "val_loss": {"direction": "min", "observations": [{"value": [209.6962890625], "step": 0}]}, "val_auc": {"direction": "min", "observations": [{"value": [0.5], "step": 0}]}}}, "score": 0.5295683145523071, "best_step": 0, "status": "COMPLETED"}