{"trial_id": "5a91a685adf0eeff0162b82b3e4842d8", "hyperparameters": {"space": [{"class_name": "Int", "config": {"name": "units_1", "default": null, "conditions": [], "min_value": 4, "max_value": 32, "step": 2, "sampling": null}}, {"class_name": "Int", "config": {"name": "units_2", "default": null, "conditions": [], "min_value": 4, "max_value": 32, "step": 2, "sampling": null}}, {"class_name": "Int", "config": {"name": "units_3", "default": null, "conditions": [], "min_value": 4, "max_value": 32, "step": 2, "sampling": null}}], "values": {"units_1": 20, "units_2": 30, "units_3": 10, "tuner/epochs": 7, "tuner/initial_epoch": 0, "tuner/bracket": 4, "tuner/round": 0}}, "metrics": {"metrics": {"loss": {"direction": "min", "observations": [{"value": [194.53782653808594], "step": 0}]}, "auc": {"direction": "max", "observations": [{"value": [0.5400269627571106], "step": 0}]}, "val_loss": {"direction": "min", "observations": [{"value": [166.30345153808594], "step": 0}]}, "val_auc": {"direction": "min", "observations": [{"value": [0.5021636486053467], "step": 0}]}}}, "score": 0.5400269627571106, "best_step": 0, "status": "COMPLETED"}