{"trial_id": "32054010f8054f6ce5ba380db1e993e7", "hyperparameters": {"space": [{"class_name": "Int", "config": {"name": "units_1", "default": null, "conditions": [], "min_value": 4, "max_value": 32, "step": 2, "sampling": null}}, {"class_name": "Int", "config": {"name": "units_2", "default": null, "conditions": [], "min_value": 4, "max_value": 32, "step": 2, "sampling": null}}, {"class_name": "Int", "config": {"name": "units_3", "default": null, "conditions": [], "min_value": 4, "max_value": 32, "step": 2, "sampling": null}}], "values": {"units_1": 16, "units_2": 28, "units_3": 20, "tuner/epochs": 7, "tuner/initial_epoch": 0, "tuner/bracket": 4, "tuner/round": 0}}, "metrics": {"metrics": {"loss": {"direction": "min", "observations": [{"value": [334.0208740234375], "step": 0}]}, "auc": {"direction": "max", "observations": [{"value": [0.5361061692237854], "step": 0}]}, "val_loss": {"direction": "min", "observations": [{"value": [69.19184875488281], "step": 0}]}, "val_auc": {"direction": "min", "observations": [{"value": [0.49534884095191956], "step": 0}]}}}, "score": 0.5361061692237854, "best_step": 0, "status": "COMPLETED"}