{"trial_id": "e062fb1bb1470a99fc6b4ec72628e619", "hyperparameters": {"space": [{"class_name": "Int", "config": {"name": "units_1", "default": null, "conditions": [], "min_value": 4, "max_value": 32, "step": 2, "sampling": null}}, {"class_name": "Choice", "config": {"name": "dense_activation_1", "default": "relu", "conditions": [], "values": ["relu", "tanh", "sigmoid"], "ordered": false}}, {"class_name": "Int", "config": {"name": "units_2", "default": null, "conditions": [], "min_value": 4, "max_value": 32, "step": 2, "sampling": null}}, {"class_name": "Choice", "config": {"name": "dense_activation_2", "default": "relu", "conditions": [], "values": ["relu", "tanh", "sigmoid"], "ordered": false}}, {"class_name": "Int", "config": {"name": "units_3", "default": null, "conditions": [], "min_value": 4, "max_value": 32, "step": 2, "sampling": null}}, {"class_name": "Choice", "config": {"name": "dense_activation_3", "default": "relu", "conditions": [], "values": ["relu", "tanh", "sigmoid"], "ordered": false}}, {"class_name": "Int", "config": {"name": "units_4", "default": null, "conditions": [], "min_value": 4, "max_value": 32, "step": 2, "sampling": null}}, {"class_name": "Choice", "config": {"name": "dense_activation_4", "default": "relu", "conditions": [], "values": ["relu", "tanh", "sigmoid"], "ordered": false}}, {"class_name": "Int", "config": {"name": "units_5", "default": null, "conditions": [], "min_value": 4, "max_value": 32, "step": 2, "sampling": null}}, {"class_name": "Choice", "config": {"name": "dense_activation_5", "default": "relu", "conditions": [], "values": ["relu", "tanh", "sigmoid"], "ordered": false}}], "values": {"units_1": 20, "dense_activation_1": "tanh", "units_2": 26, "dense_activation_2": "relu", "units_3": 32, "dense_activation_3": "relu", "units_4": 20, "dense_activation_4": "relu", "units_5": 4, "dense_activation_5": "sigmoid", "tuner/epochs": 4, "tuner/initial_epoch": 2, "tuner/bracket": 4, "tuner/round": 1, "tuner/trial_id": "08db851795b611fdf94581c5d0223b6a"}}, "metrics": {"metrics": {"loss": {"direction": "min", "observations": [{"value": [0.7958973050117493], "step": 0}]}, "auc": {"direction": "max", "observations": [{"value": [0.5352343320846558], "step": 0}]}, "val_loss": {"direction": "min", "observations": [{"value": [0.7333041429519653], "step": 0}]}, "val_auc": {"direction": "min", "observations": [{"value": [0.4437645673751831], "step": 0}]}}}, "score": 0.5352343320846558, "best_step": 0, "status": "COMPLETED"}