{"trial_id": "6511811d4ed4bc52a0f80c1af4b05873", "hyperparameters": {"space": [{"class_name": "Int", "config": {"name": "units_1", "default": null, "conditions": [], "min_value": 4, "max_value": 32, "step": 2, "sampling": null}}, {"class_name": "Int", "config": {"name": "units_2", "default": null, "conditions": [], "min_value": 4, "max_value": 32, "step": 2, "sampling": null}}, {"class_name": "Int", "config": {"name": "units_3", "default": null, "conditions": [], "min_value": 4, "max_value": 32, "step": 2, "sampling": null}}], "values": {"units_1": 28, "units_2": 24, "units_3": 20, "tuner/epochs": 2, "tuner/initial_epoch": 0, "tuner/bracket": 5, "tuner/round": 0}}, "metrics": {"metrics": {"loss": {"direction": "min", "observations": [{"value": [54.03315353393555], "step": 0}]}, "auc": {"direction": "max", "observations": [{"value": [0.5228692293167114], "step": 0}]}, "val_loss": {"direction": "min", "observations": [{"value": [15.561168670654297], "step": 0}]}, "val_auc": {"direction": "min", "observations": [{"value": [0.5375850200653076], "step": 0}]}}}, "score": 0.5228692293167114, "best_step": 0, "status": "COMPLETED"}