{"trial_id": "0b33d2802506b80b4d09879a2cf3b5d5", "hyperparameters": {"space": [{"class_name": "Int", "config": {"name": "units_1", "default": null, "conditions": [], "min_value": 4, "max_value": 32, "step": 2, "sampling": null}}, {"class_name": "Choice", "config": {"name": "dense_activation_1", "default": "relu", "conditions": [], "values": ["relu", "tanh", "sigmoid"], "ordered": false}}, {"class_name": "Int", "config": {"name": "units_2", "default": null, "conditions": [], "min_value": 4, "max_value": 32, "step": 2, "sampling": null}}, {"class_name": "Choice", "config": {"name": "dense_activation_2", "default": "relu", "conditions": [], "values": ["relu", "tanh", "sigmoid"], "ordered": false}}], "values": {"units_1": 10, "dense_activation_1": "relu", "units_2": 22, "dense_activation_2": "relu", "tuner/epochs": 23, "tuner/initial_epoch": 0, "tuner/bracket": 2, "tuner/round": 0}}, "metrics": {"metrics": {"loss": {"direction": "min", "observations": [{"value": [139.6328887939453], "step": 0}]}, "auc": {"direction": "max", "observations": [{"value": [0.5367070436477661], "step": 0}]}, "val_loss": {"direction": "min", "observations": [{"value": [70.59851837158203], "step": 0}]}, "val_auc": {"direction": "min", "observations": [{"value": [0.5454545021057129], "step": 0}]}}}, "score": 0.5367070436477661, "best_step": 0, "status": "COMPLETED"}