{"trial_id": "9cdf8f5dca9656616fc3962e55a8f40f", "hyperparameters": {"space": [{"class_name": "Int", "config": {"name": "units_1", "default": null, "conditions": [], "min_value": 4, "max_value": 32, "step": 2, "sampling": null}}, {"class_name": "Int", "config": {"name": "units_2", "default": null, "conditions": [], "min_value": 4, "max_value": 32, "step": 2, "sampling": null}}], "values": {"units_1": 24, "units_2": 24, "tuner/epochs": 3, "tuner/initial_epoch": 0, "tuner/bracket": 4, "tuner/round": 0}}, "metrics": {"metrics": {"loss": {"direction": "min", "observations": [{"value": [677.427734375], "step": 0}]}, "auc": {"direction": "max", "observations": [{"value": [0.501702606678009], "step": 0}]}, "val_loss": {"direction": "min", "observations": [{"value": [550.9930419921875], "step": 0}]}, "val_auc": {"direction": "min", "observations": [{"value": [0.5], "step": 0}]}}}, "score": 0.501702606678009, "best_step": 0, "status": "COMPLETED"}