{"trial_id": "3396aafb2ffaf05d57087ccaf370b62c", "hyperparameters": {"space": [{"class_name": "Int", "config": {"name": "units_1", "default": null, "conditions": [], "min_value": 4, "max_value": 32, "step": 2, "sampling": null}}, {"class_name": "Choice", "config": {"name": "dense_activation_1", "default": "relu", "conditions": [], "values": ["relu", "tanh", "sigmoid"], "ordered": false}}, {"class_name": "Int", "config": {"name": "units_2", "default": null, "conditions": [], "min_value": 4, "max_value": 32, "step": 2, "sampling": null}}, {"class_name": "Choice", "config": {"name": "dense_activation_2", "default": "relu", "conditions": [], "values": ["relu", "tanh", "sigmoid"], "ordered": false}}], "values": {"units_1": 12, "dense_activation_1": "tanh", "units_2": 12, "dense_activation_2": "tanh", "tuner/epochs": 2, "tuner/initial_epoch": 0, "tuner/bracket": 5, "tuner/round": 0}}, "metrics": {"metrics": {"loss": {"direction": "min", "observations": [{"value": [0.7859523892402649], "step": 0}]}, "auc": {"direction": "max", "observations": [{"value": [0.524450421333313], "step": 0}]}, "val_loss": {"direction": "min", "observations": [{"value": [0.679661214351654], "step": 0}]}, "val_auc": {"direction": "min", "observations": [{"value": [0.604459822177887], "step": 0}]}}}, "score": 0.524450421333313, "best_step": 0, "status": "COMPLETED"}